meteora/__init__.py
meteora/clients/__init__.py
meteora/clients/aemet.py
meteora/clients/agrometeo.py
meteora/clients/awel.py
meteora/clients/base.py
meteora/clients/iem.py
meteora/clients/meteocat.py
meteora/clients/meteoswiss.py
meteora/clients/mixins/__init__.py
meteora/clients/mixins/auth.py
meteora/clients/mixins/stations.py
meteora/clients/mixins/variables.py
meteora/clients/netatmo.py
meteora/clients/noaa.py
meteora/clients/ugz.py
meteora/climate_indices.py
meteora/optional.py
meteora/qc.py
meteora/settings.py
meteora/units.py
meteora/utils.py
meteora-0.12.0.dist-info/licenses/LICENSE
meteora-0.12.0.dist-info/WHEEL
meteora-0.12.0.dist-info/METADATA
meteora-0.12.0.dist-info/RECORD
