Metadata-Version: 2.4
Name: meteora
Version: 0.12.0
Summary: Pythonic interface to access data from meteorological stations
Author: Martí Bosch
Author-email: Martí Bosch <marti.bosch@epfl.ch>
License-Expression: GPL-3.0-or-later
License-File: LICENSE
Classifier: Natural Language :: English
Classifier: Programming Language :: Python :: 3
Classifier: Programming Language :: Python :: 3.10
Classifier: Programming Language :: Python :: 3.11
Classifier: Programming Language :: Python :: 3.12
Classifier: Programming Language :: Python :: 3.13
Requires-Dist: dask
Requires-Dist: geopandas>=1.0.0
Requires-Dist: matplotlib
Requires-Dist: pint
Requires-Dist: pint-pandas
Requires-Dist: pooch
Requires-Dist: pyregeon
Requires-Dist: requests
Requires-Dist: requests-cache
Requires-Dist: requests-oauthlib
Requires-Dist: tqdm
Requires-Dist: contextily ; extra == 'cx'
Requires-Dist: build ; extra == 'dev'
Requires-Dist: commitizen ; extra == 'dev'
Requires-Dist: pip ; extra == 'dev'
Requires-Dist: pre-commit ; extra == 'dev'
Requires-Dist: toml ; extra == 'dev'
Requires-Dist: twine ; extra == 'dev'
Requires-Dist: myst-parser ; extra == 'doc'
Requires-Dist: myst-nb ; extra == 'doc'
Requires-Dist: pydata-sphinx-theme ; extra == 'doc'
Requires-Dist: sphinx ; extra == 'doc'
Requires-Dist: sphinxcontrib-bibtex ; extra == 'doc'
Requires-Dist: sphinxemoji ; extra == 'doc'
Requires-Dist: osmnx ; extra == 'ox'
Requires-Dist: seaborn ; extra == 'qc'
Requires-Dist: statsmodels ; extra == 'qc'
Requires-Dist: coverage[toml] ; extra == 'test'
Requires-Dist: pook ; extra == 'test'
Requires-Dist: pytest ; extra == 'test'
Requires-Dist: pytest-cov ; extra == 'test'
Requires-Dist: python-dotenv[cli] ; extra == 'test'
Requires-Dist: requests-mock ; extra == 'test'
Requires-Dist: ruff ; extra == 'test'
Requires-Dist: ecmwf-datastores-client ; extra == 'user-guide'
Requires-Dist: netcdf4 ; extra == 'user-guide'
Requires-Dist: zarr ; extra == 'user-guide'
Requires-Dist: xarray ; extra == 'xclim'
Requires-Dist: xclim ; extra == 'xclim'
Requires-Dist: xarray ; extra == 'xvec'
Requires-Dist: xvec>=0.5.0 ; extra == 'xvec'
Requires-Python: >=3.10
Project-URL: Repository, https://github.com/martibosch/meteora
Provides-Extra: cx
Provides-Extra: dev
Provides-Extra: doc
Provides-Extra: ox
Provides-Extra: qc
Provides-Extra: test
Provides-Extra: user-guide
Provides-Extra: xclim
Provides-Extra: xvec
